antiplagiat/__init__.py
antiplagiat/__version__.py
antiplagiat/api.py
antiplagiat/exceptions.py
antiplagiat/helpers.py
func_tests/__init__.py
func_tests/test_adv_report.py
func_tests/test_api.py
advego_antiplagiat_api-1.1.0.dist-info/LICENSE
advego_antiplagiat_api-1.1.0.dist-info/METADATA
advego_antiplagiat_api-1.1.0.dist-info/WHEEL
advego_antiplagiat_api-1.1.0.dist-info/top_level.txt
advego_antiplagiat_api-1.1.0.dist-info/RECORD
