Metadata-Version: 2.1
Name: advego-antiplagiat-api
Version: 1.1.0
Summary: Неофициальный клиент для работы с сервисом антиплагиата от advego.com.
Home-page: https://github.com/V-ampire/advego-antiplagiat-api
Author: V-ampire
Author-email: webjob010@gmail.com
License: MIT
Keywords: antiplagiat,advego,api,wrapper,sdk,integration,v-ampire,lib
Platform: UNKNOWN
Classifier: License :: OSI Approved :: MIT License
Classifier: Development Status :: 5 - Production/Stable
Classifier: Intended Audience :: Developers
Classifier: Operating System :: Unix
Classifier: Topic :: Software Development :: Libraries
Classifier: Programming Language :: Python :: 3
Classifier: Programming Language :: Python :: 3.8
Classifier: Programming Language :: Python :: Implementation :: CPython
Requires-Python: >=3.8.0
Requires-Dist: requests
